{
    "timeCasa": "Portuguesa Santista",
    "timeVisitante": "CA Juventus",
    "dataJogo": "14/03/2021",
    "horaJogo": "15:00:00",
    "valorAposta": 2,
    "data": "14/03/2021",
    "hora": "09:38:09"
}, {
    "timeCasa": "Portuguesa Santista",
    "timeVisitante": "CA Juventus",
    "dataJogo": "14/03/2021",
    "horaJogo": "15:00:00",
    "valorAposta": 2,
    "data": "14/03/2021",
    "hora": "09:38:09"
}, {
    "timeCasa": "Portuguesa Santista",
    "timeVisitante": "CA Juventus",
    "dataJogo": "14/03/2021",
    "horaJogo": "15:00:00",
    "valorAposta": 2,
    "data": "14/03/2021",
    "hora": "09:38:09",
    "statusAposta": "Vencedor do Encontro"
}, {
    "timeCasa": "Portuguesa Santista",
    "timeVisitante": "CA Juventus",
    "dataJogo": "14/03/2021",
    "horaJogo": "15:00:00",
    "valorAposta": 2,
    "data": "14/03/2021",
    "hora": "09:38:09",
    "statusAposta": "Vencedor do Encontro",
    "pontos": "Visitante 4.24"
},